{
  "taskId": "2.3",
  "required_gates": [
    "docs",
    "reviewer",
    "test_engineer"
  ],
  "gates": {
    "reviewer": {
      "sessionId": "ses_2db8ff78fffeVukN3GmW6bM2ey",
      "timestamp": "2026-03-25T12:33:06.866Z",
      "agent": "reviewer"
    },
    "test_engineer": {
      "sessionId": "ses_2db8ff78fffeVukN3GmW6bM2ey",
      "timestamp": "2026-03-25T12:33:26.832Z",
      "agent": "test_engineer"
    },
    "docs": {
      "sessionId": "ses_2db8ff78fffeVukN3GmW6bM2ey",
      "timestamp": "2026-03-25T12:35:44.253Z",
      "agent": "docs"
    }
  }
}